setup.py
js_prob_distributions/Binomialdistribution.py
js_prob_distributions/Gaussiandistribution.py
js_prob_distributions/Generaldistribution.py
js_prob_distributions/__init__.py
js_prob_distributions.egg-info/PKG-INFO
js_prob_distributions.egg-info/SOURCES.txt
js_prob_distributions.egg-info/dependency_links.txt
js_prob_distributions.egg-info/not-zip-safe
js_prob_distributions.egg-info/top_level.txt