Metadata-Version: 1.0
Name: js-prob-distributions
Version: 0.1
Summary: Gaussian and Binomial distributions
Home-page: UNKNOWN
Author: Jatin Singh
Author-email: UNKNOWN
License: UNKNOWN
Platform: UNKNOWN
